hdfs3/__init__.py
hdfs3/_pyarrow.py
hdfs3/_version.py
hdfs3/compatibility.py
hdfs3/conf.py
hdfs3/core.py
hdfs3/dask.py
hdfs3/lib.py
hdfs3/mapping.py
hdfs3/utils.py
hdfs3-0.3.0.dist-info/DESCRIPTION.rst
hdfs3-0.3.0.dist-info/METADATA
hdfs3-0.3.0.dist-info/RECORD
hdfs3-0.3.0.dist-info/WHEEL
hdfs3-0.3.0.dist-info/metadata.json
hdfs3-0.3.0.dist-info/top_level.txt
