Metadata-Version: 1.0
Name: hdfs3
Version: 0.3.0
Summary: Python wrappers for libhdfs3, a native HDFS client
Home-page: http://github.com/dask/hdfs3/
Author: Martin Durant
Author-email: mdurant@continuum.io
License: BSD
Keywords: hdfs
Platform: UNKNOWN
